{"normal": {"lp": {"frequency": 1, "duration": 60, "samples": 3600, "wait": 45, "stableFactor": 2}, "bdys": {"samplesPerSpeed": 10, "frequency": 1, "samples": 3600, "speeds": "-4,-3,-2,-1,0,1,2,3,4"}, "lp_cfx": {"duration": 60, "wait": 60, "repetation": "2", "powerDown": 60}, "bdys_cfx": {"repetation": "2", "powerDown": 60}}, "low": {"lp": {"frequency": "1", "duration": 60, "samples": 3600, "wait": 45, "stableFactor": 2}, "bdys": {"samplesPerSpeed": 10, "frequency": 1, "samples": 3600, "speeds": "-4,-3,-2,-1,0,1,2,3,4"}}, "high": {"lp": {"frequency": "1", "duration": 60, "samples": 3600, "wait": 45, "stableFactor": 2}, "bdys": {"samplesPerSpeed": 10, "frequency": 1, "samples": 3600, "speeds": "-4,-3,-2,-1,0,1,2,3,4"}}}